hampel_filter/__init__.py
hampel_filter/hampel_filter.py
hampel_filter-0.0.4.dist-info/METADATA
hampel_filter-0.0.4.dist-info/WHEEL
hampel_filter-0.0.4.dist-info/licenses/LICENSE
hampel_filter-0.0.4.dist-info/RECORD
