Metadata-Version: 2.4
Name: hampel_filter
Version: 0.0.4
Summary: Hampel Filter with numba JIT parallelization
Project-URL: Homepage, https://github.com/huangzesen/hampel_filter_public
Project-URL: Issues, https://github.com/huangzesen/hampel_filter_public/issues
Author-email: Zesen Huang <huangzs1997@gmail.com>
License-File: LICENSE
Classifier: License :: OSI Approved :: MIT License
Classifier: Operating System :: OS Independent
Classifier: Programming Language :: Python :: 3
Requires-Python: <3.13,>=3.10
Requires-Dist: numba
Requires-Dist: numpy
Requires-Dist: pandas
